qt_interface_utils/__init__.py
qt_interface_utils/about_dialog.py
qt_interface_utils/license_dialog.py
qt_interface_utils/messaging.py
qt_interface_utils/path_query.py
qt_interface_utils/log/__init__.py
qt_interface_utils/log/dockable_logger.py
qt_interface_utils/log/file_logger.py
qt_interface_utils/log/stdout_logging.py
qt_interface_utils/log/test/log_generator.py
qt_interface_utils-1.0.0.dist-info/METADATA
qt_interface_utils-1.0.0.dist-info/WHEEL
qt_interface_utils-1.0.0.dist-info/RECORD
