Metadata-Version: 2.4
Name: qt-interface-utils
Version: 1.0.0
Summary: An collection of utilities for working with Qt interfaces.
Requires-Python: >=3.10
Requires-Dist: coloredlogs>=15.0.1
Requires-Dist: pydantic>=2.10.6
Requires-Dist: qtpy>=2.4.3
